openfed/__init__.py
openfed-0.0.0.dist-info/LICENSE
openfed-0.0.0.dist-info/METADATA
openfed-0.0.0.dist-info/WHEEL
openfed-0.0.0.dist-info/top_level.txt
openfed-0.0.0.dist-info/RECORD
